{
  "project_info": {
    "project_number": "947251316245",
    "project_id": "eduxcel-5a44b",
    "storage_bucket": "eduxcel-5a44b.firebasestorage.app"
  },
  "client": [
    {
      "client_info": {
        "mobilesdk_app_id": "1:947251316245:android:c3c440d1475ba49643b01c",
        "android_client_info": {
          "package_name": "com.example.eduxcel"
        }
      },
      "oauth_client": [
        {
          "client_id": "947251316245-gkujo048k15i93hc7g4rd0sstgrhb33n.apps.googleusercontent.com",
          "client_type": 1,
          "android_info": {
            "package_name": "com.example.eduxcel",
            "certificate_hash": "5b35c661a1fa726816ad7fe08ddcb43ff549d10c"
          }
        },
        {
          "client_id": "947251316245-t6f5iotprj122jrc9r8pddltl8rf9b2h.apps.googleusercontent.com",
          "client_type": 3
        }
      ],
      "api_key": [
        {
          "current_key": "AIzaSyCWQlWNYlz0M24KsduAk6S0Hww2J1tniJ8"
        }
      ],
      "services": {
        "appinvite_service": {
          "other_platform_oauth_client": [
            {
              "client_id": "947251316245-t6f5iotprj122jrc9r8pddltl8rf9b2h.apps.googleusercontent.com",
              "client_type": 3
            },
            {
              "client_id": "947251316245-qqgc7j890b3rup4v2dlented3pjq9tst.apps.googleusercontent.com",
              "client_type": 2,
              "ios_info": {
                "bundle_id": "com.example.eduxcel"
              }
            }
          ]
        }
      }
    }
  ],
  "configuration_version": "1"
}